LICENSE
MANIFEST.in
README.rst
setup.py
cube/__init__.py
cube/event.py
cube/expression.py
cube/filters.py
cube/time_utils.py
cube/tests/__init__.py
cube/tests/test_compound_metric_expression.py
cube/tests/test_event_expression.py
cube/tests/test_filters.py
cube/tests/test_metric_expression.py
cube/tests/test_time_utils.py
cube_client.egg-info/PKG-INFO
cube_client.egg-info/SOURCES.txt
cube_client.egg-info/dependency_links.txt
cube_client.egg-info/not-zip-safe
cube_client.egg-info/requires.txt
cube_client.egg-info/top_level.txt