Metadata-Version: 1.1
Name: cube-client
Version: 0.2.0
Summary: A Python client for Cube: Time Series Data Collection & Analysis
Home-page: https://github.com/tsileo/cube-client
Author: Thomas Sileo
Author-email: thomas.sileo@gmail.com
License: MIT
Keywords: cube time series
Platform: UNKNOWN
Classifier: Development Status :: 4 - Beta
Classifier: Intended Audience :: Developers
Classifier: Topic :: Database
Classifier: License :: OSI Approved :: MIT License
Classifier: Programming Language :: Python
